[
    {
        "D1": 110.0,
        "D2": 2.0,
        "D3": 2.0,
        "D4": 180.0,
        "D5": 1.5,
        "D6": 10.5,
        "D7": 10.0,
        "D8": 70.0,
        "D9": 25.0
    },
    {
        "D1": 130.0,
        "D2": 3.0,
        "D3": 2.0,
        "D4": 210.0,
        "D5": 2.0,
        "D6": 18.0,
        "D7": 8.0,
        "D8": 100.0,
        "D9": 25.0
    },
    {
        "D1": 110.0,
        "D2": 6.0,
        "D3": 2.0,
        "D4": 290.0,
        "D5": 2.0,
        "D6": 17.0,
        "D7": 1.0,
        "D8": 105.0,
        "D9": 25.0
    },
    {
        "D1": 120.0,
        "D2": 1.0,
        "D3": 3.0,
        "D4": 210.0,
        "D5": 0.0,
        "D6": 13.0,
        "D7": 9.0,
        "D8": 45.0,
        "D9": 25.0
    },
    {
        "D1": 110.0,
        "D2": 3.0,
        "D3": 2.0,
        "D4": 140.0,
        "D5": 2.0,
        "D6": 13.0,
        "D7": 7.0,
        "D8": 105.0,
        "D9": 25.0
    },
    {
        "D1": 110.0,
        "D2": 1.0,
        "D3": 1.0,
        "D4": 180.0,
        "D5": 0.0,
        "D6": 12.0,
        "D7": 13.0,
        "D8": 55.0,
        "D9": 25.0
    },
    {
        "D1": 110.0,
        "D2": 1.0,
        "D3": 1.0,
        "D4": 180.0,
        "D5": 0.0,
        "D6": 12.0,
        "D7": 13.0,
        "D8": 65.0,
        "D9": 25.0
    },
    {
        "D1": 100.0,
        "D2": 2.0,
        "D3": 1.0,
        "D4": 140.0,
        "D5": 2.0,
        "D6": 11.0,
        "D7": 10.0,
        "D8": 120.0,
        "D9": 25.0
    },
    {
        "D1": 110.0,
        "D2": 1.0,
        "D3": 1.0,
        "D4": 280.0,
        "D5": 0.0,
        "D6": 15.0,
        "D7": 9.0,
        "D8": 45.0,
        "D9": 25.0
    },
    {
        "D1": 110.0,
        "D2": 3.0,
        "D3": 1.0,
        "D4": 250.0,
        "D5": 1.5,
        "D6": 11.5,
        "D7": 10.0,
        "D8": 90.0,
        "D9": 25.0
    },
    {
        "D1": 110.0,
        "D2": 2.0,
        "D3": 1.0,
        "D4": 260.0,
        "D5": 0.0,
        "D6": 21.0,
        "D7": 3.0,
        "D8": 40.0,
        "D9": 25.0
    },
    {
        "D1": 110.0,
        "D2": 2.0,
        "D3": 1.0,
        "D4": 180.0,
        "D5": 0.0,
        "D6": 12.0,
        "D7": 12.0,
        "D8": 55.0,
        "D9": 25.0
    },
    {
        "D1": 100.0,
        "D2": 2.0,
        "D3": 1.0,
        "D4": 220.0,
        "D5": 2.0,
        "D6": 15.0,
        "D7": 6.0,
        "D8": 90.0,
        "D9": 25.0
    },
    {
        "D1": 130.0,
        "D2": 3.0,
        "D3": 2.0,
        "D4": 170.0,
        "D5": 1.5,
        "D6": 13.5,
        "D7": 10.0,
        "D8": 120.0,
        "D9": 25.0
    },
    {
        "D1": 100.0,
        "D2": 3.0,
        "D3": 2.0,
        "D4": 140.0,
        "D5": 2.5,
        "D6": 10.5,
        "D7": 8.0,
        "D8": 140.0,
        "D9": 25.0
    },
    {
        "D1": 110.0,
        "D2": 2.0,
        "D3": 1.0,
        "D4": 200.0,
        "D5": 0.0,
        "D6": 21.0,
        "D7": 3.0,
        "D8": 35.0,
        "D9": 100.0
    },
    {
        "D1": 140.0,
        "D2": 3.0,
        "D3": 1.0,
        "D4": 190.0,
        "D5": 4.0,
        "D6": 15.0,
        "D7": 14.0,
        "D8": 230.0,
        "D9": 100.0
    },
    {
        "D1": 100.0,
        "D2": 3.0,
        "D3": 1.0,
        "D4": 200.0,
        "D5": 3.0,
        "D6": 16.0,
        "D7": 3.0,
        "D8": 110.0,
        "D9": 100.0
    },
    {
        "D1": 110.0,
        "D2": 2.0,
        "D3": 1.0,
        "D4": 250.0,
        "D5": 0.0,
        "D6": 21.0,
        "D7": 3.0,
        "D8": 60.0,
        "D9": 25.0
    },
    {
        "D1": 110.0,
        "D2": 1.0,
        "D3": 1.0,
        "D4": 140.0,
        "D5": 0.0,
        "D6": 13.0,
        "D7": 12.0,
        "D8": 25.0,
        "D9": 25.0
    },
    {
        "D1": 100.0,
        "D2": 3.0,
        "D3": 1.0,
        "D4": 200.0,
        "D5": 3.0,
        "D6": 17.0,
        "D7": 3.0,
        "D8": 110.0,
        "D9": 25.0
    },
    {
        "D1": 110.0,
        "D2": 2.0,
        "D3": 1.0,
        "D4": 200.0,
        "D5": 1.0,
        "D6": 16.0,
        "D7": 8.0,
        "D8": 60.0,
        "D9": 25.0
    },
    {
        "D1": 70.0,
        "D2": 4.0,
        "D3": 1.0,
        "D4": 260.0,
        "D5": 9.0,
        "D6": 7.0,
        "D7": 5.0,
        "D8": 320.0,
        "D9": 25.0
    },
    {
        "D1": 50.0,
        "D2": 4.0,
        "D3": 0.0,
        "D4": 140.0,
        "D5": 14.0,
        "D6": 8.0,
        "D7": 0.0,
        "D8": 330.0,
        "D9": 25.0
    },
    {
        "D1": 110.0,
        "D2": 2.0,
        "D3": 0.0,
        "D4": 125.0,
        "D5": 1.0,
        "D6": 11.0,
        "D7": 14.0,
        "D8": 30.0,
        "D9": 25.0
    },
    {
        "D1": 100.0,
        "D2": 2.0,
        "D3": 0.0,
        "D4": 290.0,
        "D5": 1.0,
        "D6": 21.0,
        "D7": 2.0,
        "D8": 35.0,
        "D9": 25.0
    },
    {
        "D1": 110.0,
        "D2": 1.0,
        "D3": 0.0,
        "D4": 90.0,
        "D5": 1.0,
        "D6": 13.0,
        "D7": 12.0,
        "D8": 20.0,
        "D9": 25.0
    },
    {
        "D1": 110.0,
        "D2": 3.0,
        "D3": 3.0,
        "D4": 140.0,
        "D5": 4.0,
        "D6": 10.0,
        "D7": 7.0,
        "D8": 160.0,
        "D9": 25.0
    },
    {
        "D1": 110.0,
        "D2": 2.0,
        "D3": 0.0,
        "D4": 220.0,
        "D5": 1.0,
        "D6": 21.0,
        "D7": 3.0,
        "D8": 30.0,
        "D9": 25.0
    },
    {
        "D1": 110.0,
        "D2": 2.0,
        "D3": 1.0,
        "D4": 125.0,
        "D5": 1.0,
        "D6": 11.0,
        "D7": 13.0,
        "D8": 30.0,
        "D9": 25.0
    },
    {
        "D1": 110.0,
        "D2": 1.0,
        "D3": 0.0,
        "D4": 200.0,
        "D5": 1.0,
        "D6": 14.0,
        "D7": 11.0,
        "D8": 25.0,
        "D9": 25.0
    },
    {
        "D1": 100.0,
        "D2": 3.0,
        "D3": 0.0,
        "D4": 0.0,
        "D5": 3.0,
        "D6": 14.0,
        "D7": 7.0,
        "D8": 100.0,
        "D9": 25.0
    },
    {
        "D1": 120.0,
        "D2": 3.0,
        "D3": 0.0,
        "D4": 240.0,
        "D5": 5.0,
        "D6": 14.0,
        "D7": 12.0,
        "D8": 190.0,
        "D9": 25.0
    },
    {
        "D1": 110.0,
        "D2": 2.0,
        "D3": 1.0,
        "D4": 170.0,
        "D5": 1.0,
        "D6": 17.0,
        "D7": 6.0,
        "D8": 60.0,
        "D9": 100.0
    },
    {
        "D1": 140.0,
        "D2": 3.0,
        "D3": 1.0,
        "D4": 170.0,
        "D5": 2.0,
        "D6": 20.0,
        "D7": 9.0,
        "D8": 95.0,
        "D9": 100.0
    },
    {
        "D1": 160.0,
        "D2": 3.0,
        "D3": 2.0,
        "D4": 150.0,
        "D5": 3.0,
        "D6": 17.0,
        "D7": 13.0,
        "D8": 160.0,
        "D9": 25.0
    },
    {
        "D1": 120.0,
        "D2": 2.0,
        "D3": 1.0,
        "D4": 190.0,
        "D5": 0.0,
        "D6": 15.0,
        "D7": 9.0,
        "D8": 40.0,
        "D9": 25.0
    },
    {
        "D1": 140.0,
        "D2": 3.0,
        "D3": 2.0,
        "D4": 220.0,
        "D5": 3.0,
        "D6": 21.0,
        "D7": 7.0,
        "D8": 130.0,
        "D9": 25.0
    },
    {
        "D1": 90.0,
        "D2": 3.0,
        "D3": 0.0,
        "D4": 170.0,
        "D5": 3.0,
        "D6": 18.0,
        "D7": 2.0,
        "D8": 90.0,
        "D9": 25.0
    },
    {
        "D1": 100.0,
        "D2": 3.0,
        "D3": 0.0,
        "D4": 320.0,
        "D5": 1.0,
        "D6": 20.0,
        "D7": 3.0,
        "D8": 45.0,
        "D9": 100.0
    },
    {
        "D1": 120.0,
        "D2": 3.0,
        "D3": 1.0,
        "D4": 210.0,
        "D5": 5.0,
        "D6": 14.0,
        "D7": 12.0,
        "D8": 240.0,
        "D9": 25.0
    },
    {
        "D1": 90.0,
        "D2": 2.0,
        "D3": 0.0,
        "D4": 0.0,
        "D5": 2.0,
        "D6": 15.0,
        "D7": 6.0,
        "D8": 110.0,
        "D9": 25.0
    },
    {
        "D1": 110.0,
        "D2": 2.0,
        "D3": 0.0,
        "D4": 290.0,
        "D5": 0.0,
        "D6": 22.0,
        "D7": 3.0,
        "D8": 35.0,
        "D9": 25.0
    },
    {
        "D1": 110.0,
        "D2": 2.0,
        "D3": 1.0,
        "D4": 70.0,
        "D5": 1.0,
        "D6": 9.0,
        "D7": 15.0,
        "D8": 40.0,
        "D9": 25.0
    },
    {
        "D1": 110.0,
        "D2": 6.0,
        "D3": 0.0,
        "D4": 230.0,
        "D5": 1.0,
        "D6": 16.0,
        "D7": 3.0,
        "D8": 55.0,
        "D9": 25.0
    },
    {
        "D1": 70.0,
        "D2": 4.0,
        "D3": 1.0,
        "D4": 130.0,
        "D5": 10.0,
        "D6": 5.0,
        "D7": 6.0,
        "D8": 280.0,
        "D9": 25.0
    },
    {
        "D1": 80.0,
        "D2": 2.0,
        "D3": 0.0,
        "D4": 0.0,
        "D5": 3.0,
        "D6": 16.0,
        "D7": 0.0,
        "D8": 95.0,
        "D9": 0.0
    },
    {
        "D1": 90.0,
        "D2": 3.0,
        "D3": 0.0,
        "D4": 0.0,
        "D5": 4.0,
        "D6": 19.0,
        "D7": 0.0,
        "D8": 140.0,
        "D9": 0.0
    },
    {
        "D1": 90.0,
        "D2": 3.0,
        "D3": 0.0,
        "D4": 0.0,
        "D5": 3.0,
        "D6": 20.0,
        "D7": 0.0,
        "D8": 120.0,
        "D9": 0.0
    },
    {
        "D1": 90.0,
        "D2": 2.0,
        "D3": 0.0,
        "D4": 15.0,
        "D5": 3.0,
        "D6": 15.0,
        "D7": 5.0,
        "D8": 90.0,
        "D9": 25.0
    },
    {
        "D1": 90.0,
        "D2": 3.0,
        "D3": 0.0,
        "D4": 210.0,
        "D5": 5.0,
        "D6": 13.0,
        "D7": 5.0,
        "D8": 190.0,
        "D9": 25.0
    },
    {
        "D1": 120.0,
        "D2": 3.0,
        "D3": 2.0,
        "D4": 160.0,
        "D5": 5.0,
        "D6": 12.0,
        "D7": 10.0,
        "D8": 200.0,
        "D9": 25.0
    },
    {
        "D1": 110.0,
        "D2": 1.0,
        "D3": 1.0,
        "D4": 135.0,
        "D5": 0.0,
        "D6": 13.0,
        "D7": 12.0,
        "D8": 25.0,
        "D9": 25.0
    },
    {
        "D1": 100.0,
        "D2": 2.0,
        "D3": 0.0,
        "D4": 45.0,
        "D5": 0.0,
        "D6": 11.0,
        "D7": 15.0,
        "D8": 40.0,
        "D9": 25.0
    },
    {
        "D1": 100.0,
        "D2": 3.0,
        "D3": 1.0,
        "D4": 140.0,
        "D5": 3.0,
        "D6": 15.0,
        "D7": 5.0,
        "D8": 85.0,
        "D9": 25.0
    },
    {
        "D1": 110.0,
        "D2": 3.0,
        "D3": 0.0,
        "D4": 170.0,
        "D5": 3.0,
        "D6": 17.0,
        "D7": 3.0,
        "D8": 90.0,
        "D9": 25.0
    },
    {
        "D1": 120.0,
        "D2": 3.0,
        "D3": 3.0,
        "D4": 75.0,
        "D5": 3.0,
        "D6": 13.0,
        "D7": 4.0,
        "D8": 100.0,
        "D9": 25.0
    },
    {
        "D1": 110.0,
        "D2": 1.0,
        "D3": 0.0,
        "D4": 180.0,
        "D5": 0.0,
        "D6": 14.0,
        "D7": 11.0,
        "D8": 35.0,
        "D9": 25.0
    },
    {
        "D1": 120.0,
        "D2": 3.0,
        "D3": 1.0,
        "D4": 200.0,
        "D5": 6.0,
        "D6": 11.0,
        "D7": 14.0,
        "D8": 260.0,
        "D9": 25.0
    },
    {
        "D1": 120.0,
        "D2": 3.0,
        "D3": 5.0,
        "D4": 15.0,
        "D5": 2.0,
        "D6": 8.0,
        "D7": 8.0,
        "D8": 135.0,
        "D9": 0.0
    },
    {
        "D1": 120.0,
        "D2": 1.0,
        "D3": 2.0,
        "D4": 220.0,
        "D5": 0.0,
        "D6": 12.0,
        "D7": 12.0,
        "D8": 35.0,
        "D9": 25.0
    },
    {
        "D1": 120.0,
        "D2": 1.0,
        "D3": 2.0,
        "D4": 220.0,
        "D5": 1.0,
        "D6": 12.0,
        "D7": 11.0,
        "D8": 45.0,
        "D9": 25.0
    },
    {
        "D1": 100.0,
        "D2": 4.0,
        "D3": 2.0,
        "D4": 150.0,
        "D5": 2.0,
        "D6": 12.0,
        "D7": 6.0,
        "D8": 95.0,
        "D9": 25.0
    },
    {
        "D1": 50.0,
        "D2": 1.0,
        "D3": 0.0,
        "D4": 0.0,
        "D5": 0.0,
        "D6": 13.0,
        "D7": 0.0,
        "D8": 15.0,
        "D9": 0.0
    },
    {
        "D1": 50.0,
        "D2": 2.0,
        "D3": 0.0,
        "D4": 0.0,
        "D5": 1.0,
        "D6": 10.0,
        "D7": 0.0,
        "D8": 50.0,
        "D9": 0.0
    },
    {
        "D1": 100.0,
        "D2": 4.0,
        "D3": 1.0,
        "D4": 135.0,
        "D5": 2.0,
        "D6": 14.0,
        "D7": 6.0,
        "D8": 110.0,
        "D9": 25.0
    },
    {
        "D1": 90.0,
        "D2": 2.0,
        "D3": 1.0,
        "D4": 200.0,
        "D5": 4.0,
        "D6": 15.0,
        "D7": 6.0,
        "D8": 125.0,
        "D9": 25.0
    },
    {
        "D1": 110.0,
        "D2": 2.0,
        "D3": 0.0,
        "D4": 280.0,
        "D5": 0.0,
        "D6": 22.0,
        "D7": 3.0,
        "D8": 25.0,
        "D9": 25.0
    },
    {
        "D1": 100.0,
        "D2": 2.0,
        "D3": 0.0,
        "D4": 190.0,
        "D5": 1.0,
        "D6": 18.0,
        "D7": 5.0,
        "D8": 80.0,
        "D9": 25.0
    },
    {
        "D1": 150.0,
        "D2": 4.0,
        "D3": 3.0,
        "D4": 95.0,
        "D5": 3.0,
        "D6": 16.0,
        "D7": 11.0,
        "D8": 170.0,
        "D9": 25.0
    },
    {
        "D1": 150.0,
        "D2": 4.0,
        "D3": 3.0,
        "D4": 150.0,
        "D5": 3.0,
        "D6": 16.0,
        "D7": 11.0,
        "D8": 170.0,
        "D9": 25.0
    },
    {
        "D1": 110.0,
        "D2": 1.0,
        "D3": 0.0,
        "D4": 240.0,
        "D5": 0.0,
        "D6": 23.0,
        "D7": 2.0,
        "D8": 30.0,
        "D9": 25.0
    },
    {
        "D1": 100.0,
        "D2": 3.0,
        "D3": 1.0,
        "D4": 230.0,
        "D5": 3.0,
        "D6": 17.0,
        "D7": 3.0,
        "D8": 115.0,
        "D9": 25.0
    },
    {
        "D1": 100.0,
        "D2": 4.0,
        "D3": 1.0,
        "D4": 0.0,
        "D5": 0.0,
        "D6": 16.0,
        "D7": 3.0,
        "D8": 95.0,
        "D9": 25.0
    }
]